clip_jaxtorch/__init__.py
clip_jaxtorch/clip.py
clip_jaxtorch/resnet.py
clip_jaxtorch/vit.py
clip_jaxtorch-0.1.0.dist-info/METADATA
clip_jaxtorch-0.1.0.dist-info/WHEEL
clip_jaxtorch-0.1.0.dist-info/RECORD
